easyai/__init__.py
easyai/base.py
easyai/controlnet.py
easyai/image.py
easyai/interfaces.py
easyai/main.py
easyai/result.py
easyai/upscaler.py
easyai_sdwebui_api-0.1.5.dist-info/LICENSE
easyai_sdwebui_api-0.1.5.dist-info/WHEEL
easyai_sdwebui_api-0.1.5.dist-info/METADATA
easyai_sdwebui_api-0.1.5.dist-info/RECORD
