Metadata-Version: 2.1
Name: easyai-sdwebui-api
Version: 0.1.5
Summary: Easy SDWebUI API - Easy API for SDWebUI, forked from mix1009/sdwebuiapi
Home-page: https://github.com/freemindcore/sdwebuiapi
Author: Freemind Core
Author-email: freemindcore@icloud.com
Requires-Python: >=3.7
Classifier: Intended Audience :: Information Technology
Classifier: Intended Audience :: System Administrators
Classifier: Operating System :: OS Independent
Classifier: Topic :: Internet
Classifier: Topic :: Software Development :: Libraries :: Application Frameworks
Classifier: Topic :: Software Development :: Libraries :: Python Modules
Classifier: Topic :: Software Development :: Libraries
Classifier: Topic :: Software Development
Classifier: Typing :: Typed
Classifier: Environment :: Web Environment
Classifier: Intended Audience :: Developers
Classifier: License :: OSI Approved :: MIT License
Classifier: Programming Language :: Python :: 3
Classifier: Programming Language :: Python :: 3.7
Classifier: Programming Language :: Python :: 3.8
Classifier: Programming Language :: Python :: 3.9
Classifier: Programming Language :: Python :: 3.10
Classifier: Programming Language :: Python :: 3.11
Classifier: Programming Language :: Python :: 3 :: Only
Classifier: Topic :: Internet :: WWW/HTTP :: HTTP Servers
Classifier: Topic :: Internet :: WWW/HTTP
Requires-Dist: requests
Requires-Dist: Pillow
Requires-Dist: aiohttp
Requires-Dist: autoflake ; extra == "dev"
Requires-Dist: pre_commit ; extra == "dev"
Requires-Dist: bumpversion==0.6.0 ; extra == "dev"
Requires-Dist: pytest ; extra == "test"
Requires-Dist: pytest-cov ; extra == "test"
Requires-Dist: black ; extra == "test"
Requires-Dist: isort ; extra == "test"
Requires-Dist: flake8 ; extra == "test"
Requires-Dist: mypy==0.931 ; extra == "test"
Project-URL: Documentation, https://github.com/freemindcore/sdwebuiapi
Provides-Extra: dev
Provides-Extra: test
